pcvs/__init__.py
pcvs/graph.py
pcvs/io.py
pcvs/main.py
pcvs/backend/__init__.py
pcvs/backend/bank.py
pcvs/backend/config.py
pcvs/backend/profile.py
pcvs/backend/report.py
pcvs/backend/run.py
pcvs/backend/session.py
pcvs/backend/spack.py
pcvs/backend/utilities.py
pcvs/cli/__init__.py
pcvs/cli/cli_bank.py
pcvs/cli/cli_config.py
pcvs/cli/cli_convert.py
pcvs/cli/cli_graph.py
pcvs/cli/cli_plumbing.py
pcvs/cli/cli_profile.py
pcvs/cli/cli_remote_run.py
pcvs/cli/cli_report.py
pcvs/cli/cli_run.py
pcvs/cli/cli_session.py
pcvs/cli/cli_utilities.py
pcvs/converter/__init__.py
pcvs/converter/convert.json
pcvs/converter/result_converter.py
pcvs/converter/yaml_converter.py
pcvs/dsl/__init__.py
pcvs/dsl/analysis.py
pcvs/dsl/render.py
pcvs/helpers/__init__.py
pcvs/helpers/communications.py
pcvs/helpers/criterion.py
pcvs/helpers/exceptions.py
pcvs/helpers/git.py
pcvs/helpers/pm.py
pcvs/helpers/resource_tracker.py
pcvs/helpers/system.py
pcvs/helpers/utils.py
pcvs/orchestration/__init__.py
pcvs/orchestration/__main__.py
pcvs/orchestration/manager.py
pcvs/orchestration/publishers.py
pcvs/orchestration/runner.py
pcvs/orchestration/set.py
pcvs/plugins/__init__.py
pcvs/plugins/contrib/__init__.py
pcvs/plugins/contrib/junit.py
pcvs/plugins/contrib/mpc.py
pcvs/plugins/contrib/multijobs.py
pcvs/plugins/default/__init__.py
pcvs/plugins/default/validation.py
pcvs/schemes/compiler-scheme.yml
pcvs/schemes/criterion-scheme.yml
pcvs/schemes/group-scheme.yml
pcvs/schemes/machine-scheme.yml
pcvs/schemes/runtime-scheme.yml
pcvs/schemes/settings-scheme.yml
pcvs/schemes/te-scheme.yml
pcvs/schemes/test-result-scheme.yml
pcvs/schemes/validation-scheme.yml
pcvs/templates/config/compiler.default.yml
pcvs/templates/config/compiler.gcc.yml
pcvs/templates/config/compiler.icc.yml
pcvs/templates/config/compiler.mpi.yml
pcvs/templates/config/criterion.default.yml
pcvs/templates/config/criterion.large.yml
pcvs/templates/config/criterion.small.yml
pcvs/templates/config/group-compat.yml
pcvs-0.8.0.dist-info/licenses/AUTHORS.md
pcvs-0.8.0.dist-info/licenses/COPYING
pcvs-0.8.0.dist-info/METADATA
pcvs-0.8.0.dist-info/WHEEL
pcvs-0.8.0.dist-info/entry_points.txt
pcvs-0.8.0.dist-info/top_level.txt
pcvs-0.8.0.dist-info/RECORD
