Metadata-Version: 2.4
Name: pcvs
Version: 0.8.0
Summary: A Validation Orchestrator designed by and for software at scale.
Author-email: Julien Adam <adamj@paratools.com>, Paul Canat <pcanat@paratools.com>, Nicolas Marie <nicolas.marie@uvsq.fr>
License: CeCILL-C
Project-URL: Homepage, https://pcvs.io
Project-URL: Documentation, https://cea-hpc.github.io/pcvs/
Project-URL: Repository, https://github.com/cea-hpc/pcvs
Project-URL: Issues, https://github.com/cea-hpc/pcvs/issues
Project-URL: Changelog, https://github.com/cea-hpc/pcvs/blob/master/CHANGES
Keywords: validation,hpc,test-suite
Classifier: Topic :: Software Development :: Quality Assurance
Classifier: Topic :: Software Development :: Testing
Requires-Python: >=3.10
License-File: COPYING
License-File: AUTHORS.md
Requires-Dist: ruamel.yaml
Requires-Dist: Click>=8.0
Requires-Dist: requests
Requires-Dist: jsonschema>=3.0.0
Requires-Dist: flask
Requires-Dist: sh
Requires-Dist: rich
Requires-Dist: rich-click
Requires-Dist: pygit2<=1.14.1
Requires-Dist: textual>=0.29.0
Requires-Dist: matplotlib
Provides-Extra: dev
Requires-Dist: autopep8; extra == "dev"
Requires-Dist: darglint; extra == "dev"
Requires-Dist: pydocstyle; extra == "dev"
Requires-Dist: flake8; extra == "dev"
Requires-Dist: pylint; extra == "dev"
Requires-Dist: pytest; extra == "dev"
Requires-Dist: coverage; extra == "dev"
Requires-Dist: docstr-coverage; extra == "dev"
Requires-Dist: tox; extra == "dev"
Requires-Dist: pre-commit; extra == "dev"
Requires-Dist: isort; extra == "dev"
Requires-Dist: black; extra == "dev"
Requires-Dist: mypy; extra == "dev"
Requires-Dist: sphinx; extra == "dev"
Requires-Dist: sphinx-autodoc-typehints; extra == "dev"
Requires-Dist: sphinx-rtd-theme; extra == "dev"
Requires-Dist: textual-dev; extra == "dev"
Requires-Dist: python-lsp-server; extra == "dev"
Dynamic: license-file
